{
    "namespace": "Ngs.Engine",
    "typeMappings": {
        "int8_t": "sbyte",
        "uint8_t": "byte",
        "int16_t": "short",
        "uint16_t": "ushort",
        "int32_t": "int",
        "uint32_t": "uint",
        "int64_t": "long",
        "uint64_t": "ulong",
        "bstring": "[MarshalAs(UnmanagedType.BStr)] string",
        "ngsVector2": "Ngs.Utils.Vector2",
        "ngsVector3": "Ngs.Utils.Vector3",
        "ngsVector4": "Ngs.Utils.Vector4",
        "ngsIntVector2": "Ngs.Utils.IntVector2",
        "ngsIntVector3": "Ngs.Utils.IntVector3",
        "ngsIntVector4": "Ngs.Utils.IntVector4",
        "ngsBox2D": "Ngs.Utils.Box2D",
        "ngsTerrainVoxelInfo": "Ngs.Engine.TerrainVoxelInfo",
        "ngsFullScreenMode": "Ngs.Engine.FullScreenMode",
        "ngsWheelDeltaMode": "Ngs.Engine.WheelDeltaMode"
    }
}